django_isbn_field-0.4.dist-info/DESCRIPTION.rst
django_isbn_field-0.4.dist-info/metadata.json
django_isbn_field-0.4.dist-info/RECORD
django_isbn_field-0.4.dist-info/METADATA
django_isbn_field-0.4.dist-info/WHEEL
django_isbn_field-0.4.dist-info/top_level.txt
isbn_field/models.py
isbn_field/fields.py
isbn_field/tests.py
isbn_field/__init__.py
isbn_field/validators.py
